md3/__init__.py
md3/common/__init__.py
md3/common/date.py
md3/common/exceptions.py
md3/common/json.py
md3/common/text.py
md3/elasticsearch/__init__.py
md3_common_utils-0.0.3.data/data/LICENSE.txt
md3_common_utils-0.0.3.data/data/README.md
md3_common_utils-0.0.3.dist-info/LICENSE.txt
md3_common_utils-0.0.3.dist-info/METADATA
md3_common_utils-0.0.3.dist-info/WHEEL
md3_common_utils-0.0.3.dist-info/top_level.txt
md3_common_utils-0.0.3.dist-info/RECORD
