Metadata-Version: 2.1
Name: md3-common-utils
Version: 0.0.3
Summary: Common utils
Home-page: https://www.md3.pt
Author: MD3
Author-email: dev@md3.pt
Maintainer: MD3
Maintainer-email: dev@md3.pt
License: Apache License, Version 2.0
Keywords: utils
Platform: UNKNOWN
Classifier: Intended Audience :: Developers
Classifier: License :: OSI Approved :: Apache Software License
Classifier: Operating System :: OS Independent
Classifier: Programming Language :: Python :: 2.7
Classifier: Programming Language :: Python :: 3.2
Classifier: Programming Language :: Python :: 3.3
Classifier: Programming Language :: Python :: 3.4
Classifier: Programming Language :: Python :: 3.5
Classifier: Programming Language :: Python :: 3.6
Classifier: Programming Language :: Python :: 3.7
Classifier: Programming Language :: Python :: 3.8
Requires-Python: <=3.8.0,>=2.7
Requires-Dist: Unidecode (==1.0.22)
